laior/__init__.py
laior/agent.py
laior/benchmarking.py
laior/environment.py
laior/interpretation.py
laior/mixin.py
laior/model.py
laior/module.py
laior/ode_functions.py
laior/utils.py
laior/distributions/__init__.py
laior/distributions/utils.py
laior/distributions/EuclideanNormal/__init__.py
laior/distributions/EuclideanNormal/arguments.py
laior/distributions/EuclideanNormal/distribution.py
laior/distributions/EuclideanNormal/layers.py
laior/distributions/EuclideanNormal/prior.py
laior/distributions/HWNormal/__init__.py
laior/distributions/HWNormal/arguments.py
laior/distributions/HWNormal/distribution.py
laior/distributions/HWNormal/layers.py
laior/distributions/HWNormal/prior.py
laior/distributions/LearnablePGMNormal/__init__.py
laior/distributions/LearnablePGMNormal/arguments.py
laior/distributions/LearnablePGMNormal/distribution.py
laior/distributions/LearnablePGMNormal/layers.py
laior/distributions/LearnablePGMNormal/prior.py
laior/distributions/PGMNormal/__init__.py
laior/distributions/PGMNormal/arguments.py
laior/distributions/PGMNormal/distribution.py
laior/distributions/PGMNormal/layers.py
laior/distributions/PGMNormal/prior.py
laior/distributions/PoincareNormal/__init__.py
laior/distributions/PoincareNormal/arguments.py
laior/distributions/PoincareNormal/ars.py
laior/distributions/PoincareNormal/distribution.py
laior/distributions/PoincareNormal/hyperbolic_radius.py
laior/distributions/PoincareNormal/hyperbolic_uniform.py
laior/distributions/PoincareNormal/layers.py
laior/distributions/PoincareNormal/prior.py
laior/examples/encoder_example.py
laior/unified_models/__init__.py
laior/unified_models/base_model.py
laior/unified_models/cellblast_model.py
laior/unified_models/clear_model.py
laior/unified_models/gmvae_model.py
laior/unified_models/scalex_model.py
laior/unified_models/scdac_model.py
laior/unified_models/scdeepcluster_model.py
laior/unified_models/scdhmap_model.py
laior/unified_models/scdiffusion_model.py
laior/unified_models/scgcc_model.py
laior-0.6.0.dist-info/licenses/LICENSE
laior-0.6.0.dist-info/METADATA
laior-0.6.0.dist-info/WHEEL
laior-0.6.0.dist-info/top_level.txt
laior-0.6.0.dist-info/RECORD
